moretypes.py
moretypes-0.0.1.dist-info/LICENSE.txt
moretypes-0.0.1.dist-info/METADATA
moretypes-0.0.1.dist-info/WHEEL
moretypes-0.0.1.dist-info/top_level.txt
moretypes-0.0.1.dist-info/RECORD
