Metadata-Version: 2.1
Name: moretypes
Version: 0.0.1
Summary: A Python types extension library that allows for more even versatile data storage and referencing.
Home-page: UNKNOWN
Author: minecraftpr03
License: UNKNOWN
Platform: UNKNOWN
Classifier: Programming Language :: Python :: 3
Classifier: Programming Language :: Python :: 3.6
Classifier: Programming Language :: Python :: 3.7
Classifier: Programming Language :: Python :: 3.8
Classifier: Programming Language :: Python :: 3.9
Classifier: License :: OSI Approved :: MIT License
Classifier: Operating System :: OS Independent
